miniacsincome/__init__.py
miniacsincome/cases.py
miniacsincome/miniacsincome.py
miniacsincome-0.0.3.dist-info/licenses/LICENSE
miniacsincome-0.0.3.dist-info/WHEEL
miniacsincome-0.0.3.dist-info/METADATA
miniacsincome-0.0.3.dist-info/RECORD
