Metadata-Version: 2.4
Name: miniacsincome
Version: 0.0.3
Summary: MiniACSIncome: A benchmark for fairness verification of neural networks.
Author-email: David Boetius <david.boetius@uni-konstanz.de>
Requires-Python: >=3.10
Classifier: Programming Language :: Python :: 3
Classifier: License :: OSI Approved :: MIT License
License-File: LICENSE
Requires-Dist: torch>=1.12.1,<3.0
Requires-Dist: numpy>=1.25,<3.0
Requires-Dist: folktables==0.0.12
Requires-Dist: torchstats==0.1.0
Requires-Dist: dill==0.3.8
Requires-Dist: huggingface_hub==0.32.0
Requires-Dist: miniacsincome[recreate, test] ; extra == "all"
Requires-Dist: pandas==2.1.4 ; extra == "recreate"
Requires-Dist: seaborn==0.12.2 ; extra == "recreate"
Requires-Dist: matplotlib>=3.8.2,<3.9.0 ; extra == "recreate"
Requires-Dist: tqdm>=4.66.5,<4.67 ; extra == "recreate"
Requires-Dist: jupyter==1.1.1 ; extra == "recreate"
Requires-Dist: papermill>=2.6.0,<3.0 ; extra == "recreate"
Requires-Dist: optuna>=3.5.0,<4.0 ; extra == "recreate"
Requires-Dist: nox==2025.5.1 ; extra == "test"
Requires-Dist: pytest==8.3.5 ; extra == "test"
Project-URL: Homepage, https://github.com/sen-uni-kn/MiniACSIncome
Project-URL: Issues, https://github.com/sen-uni-kn/MiniACSIncome/issues
Project-URL: Repository, https://github.com/sen-uni-kn/MiniACSIncome.git
Provides-Extra: all
Provides-Extra: recreate
Provides-Extra: test
